pyga4/analytic/__init__.py
pyga4/analytic/analytic.py
pyga4/analytic/data_transform.py
pyga4/analytic/time_analysis.py
pyga4/model/__init__.py
pyga4/model/bigquery.py
pyga4-0.2.0.dist-info/LICENSE
pyga4-0.2.0.dist-info/METADATA
pyga4-0.2.0.dist-info/WHEEL
pyga4-0.2.0.dist-info/RECORD
