Metadata-Version: 2.1
Name: pyga4
Version: 0.2.0
Summary: Python Google Analytics 4 (GA4) Data Extraction and Analysis Toolkit
Home-page: https://github.com/Lin-jun-xiang/pyga4
License: MIT
Author: Lin-jun-xiang
Author-email: jimmy871117@gmail.com
Requires-Python: >=3.8,<4.0
Classifier: License :: OSI Approved :: MIT License
Classifier: Programming Language :: Python :: 3
Classifier: Programming Language :: Python :: 3.8
Classifier: Programming Language :: Python :: 3.9
Classifier: Programming Language :: Python :: 3.10
Classifier: Programming Language :: Python :: 3.11
Requires-Dist: google-cloud (>=0.34.0,<0.35.0)
Requires-Dist: google-cloud-bigquery (>=3.11.4,<4.0.0)
Requires-Dist: matplotlib (==3.6.2)
Requires-Dist: pandas (==1.5.3)
Requires-Dist: protobuf (==4.24.3)
Requires-Dist: pycryptodome (==3.18.0)
Project-URL: Repository, https://github.com/Lin-jun-xiang/pyga4
